<?xml version="1.0" encoding="utf-8"?>
<ArrayOfPropXMLStruct2 xmlns:xsi="http://www.w3.org/2001/XMLSchema-instance" xmlns:xsd="http://www.w3.org/2001/XMLSchema">
  <PropXMLStruct2>
    <id>104</id>
    <position>
      <X>-10721.8926</X>
      <Y>-1344.88257</Y>
      <Z>-28386.94</Z>
    </position>
    <rotation>
      <X>0</X>
      <Y>-55</Y>
      <Z>0</Z>
    </rotation>
    <scale>
      <X>1.4000001</X>
      <Y>1.4000001</Y>
      <Z>1.4000001</Z>
    </scale>
  </PropXMLStruct2>
  <PropXMLStruct2>
    <id>152</id>
    <position>
      <X>-4388.15869</X>
      <Y>-2512.31079</Y>
      <Z>-35782.86</Z>
    </position>
    <rotation>
      <X>-91</X>
      <Y>17</Y>
      <Z>4.5</Z>
    </rotation>
    <scale>
      <X>5.120023</X>
      <Y>5.120023</Y>
      <Z>5.120023</Z>
    </scale>
  </PropXMLStruct2>
  <PropXMLStruct2>
    <id>100</id>
    <position>
      <X>-4747.88232</X>
      <Y>-2717.483</Y>
      <Z>-35928.7422</Z>
    </position>
    <rotation>
      <X>0</X>
      <Y>0</Y>
      <Z>0</Z>
    </rotation>
    <scale>
      <X>1.989999</X>
      <Y>1.989999</Y>
      <Z>1.989999</Z>
    </scale>
  </PropXMLStruct2>
  <PropXMLStruct2>
    <id>102</id>
    <position>
      <X>-4688.65137</X>
      <Y>-2751.1106</Y>
      <Z>-36061.94</Z>
    </position>
    <rotation>
      <X>0</X>
      <Y>-3</Y>
      <Z>0</Z>
    </rotation>
    <scale>
      <X>2.52999854</X>
      <Y>2.52999854</Y>
      <Z>2.52999854</Z>
    </scale>
  </PropXMLStruct2>
  <PropXMLStruct2>
    <id>98</id>
    <position>
      <X>-4258.46875</X>
      <Y>-1545.00854</Y>
      <Z>-35584.17</Z>
    </position>
    <rotation>
      <X>0</X>
      <Y>23.5</Y>
      <Z>0</Z>
    </rotation>
    <scale>
      <X>8.640103</X>
      <Y>4.780015</Y>
      <Z>1</Z>
    </scale>
  </PropXMLStruct2>
  <PropXMLStruct2>
    <id>98</id>
    <position>
      <X>-5637.15332</X>
      <Y>-1605.12659</Y>
      <Z>-34952.6328</Z>
    </position>
    <rotation>
      <X>0</X>
      <Y>25.5</Y>
      <Z>0</Z>
    </rotation>
    <scale>
      <X>11.4701681</X>
      <Y>5.63003445</Y>
      <Z>1</Z>
    </scale>
  </PropXMLStruct2>
  <PropXMLStruct2>
    <id>98</id>
    <position>
      <X>-7257.78125</X>
      <Y>-1606.93945</Y>
      <Z>-34188.4531</Z>
    </position>
    <rotation>
      <X>0</X>
      <Y>25</Y>
      <Z>0</Z>
    </rotation>
    <scale>
      <X>12.340188</X>
      <Y>4.80001545</Y>
      <Z>1</Z>
    </scale>
  </PropXMLStruct2>
  <PropXMLStruct2>
    <id>98</id>
    <position>
      <X>-8860.185</X>
      <Y>-1628.60461</Y>
      <Z>-33432.6523</Z>
    </position>
    <rotation>
      <X>0</X>
      <Y>25.5</Y>
      <Z>0</Z>
    </rotation>
    <scale>
      <X>11.10016</X>
      <Y>5.0600214</Y>
      <Z>1</Z>
    </scale>
  </PropXMLStruct2>
  <PropXMLStruct2>
    <id>98</id>
    <position>
      <X>-10489.6279</X>
      <Y>-1679.17639</Y>
      <Z>-32676.6289</Z>
    </position>
    <rotation>
      <X>0</X>
      <Y>24.5</Y>
      <Z>0</Z>
    </rotation>
    <scale>
      <X>12.730197</X>
      <Y>5.140023</Y>
      <Z>1</Z>
    </scale>
  </PropXMLStruct2>
  <PropXMLStruct2>
    <id>98</id>
    <position>
      <X>-12014.3818</X>
      <Y>-1889.80225</Y>
      <Z>-32029.9414</Z>
    </position>
    <rotation>
      <X>0</X>
      <Y>21</Y>
      <Z>0</Z>
    </rotation>
    <scale>
      <X>9.050113</X>
      <Y>6.54005527</Y>
      <Z>1</Z>
    </scale>
  </PropXMLStruct2>
  <PropXMLStruct2>
    <id>98</id>
    <position>
      <X>-5252.483</X>
      <Y>-2874.15552</Y>
      <Z>-35566.47</Z>
    </position>
    <rotation>
      <X>0</X>
      <Y>25.5</Y>
      <Z>0</Z>
    </rotation>
    <scale>
      <X>17.5500183</X>
      <Y>7.30000973</Y>
      <Z>1</Z>
    </scale>
  </PropXMLStruct2>
  <PropXMLStruct2>
    <id>98</id>
    <position>
      <X>-7637.869</X>
      <Y>-2902.48633</Y>
      <Z>-34427.36</Z>
    </position>
    <rotation>
      <X>0</X>
      <Y>25.5</Y>
      <Z>0</Z>
    </rotation>
    <scale>
      <X>17.3500214</X>
      <Y>8.300014</Y>
      <Z>1</Z>
    </scale>
  </PropXMLStruct2>
  <PropXMLStruct2>
    <id>98</id>
    <position>
      <X>-10207.457</X>
      <Y>-2901.73</Y>
      <Z>-33187.4375</Z>
    </position>
    <rotation>
      <X>0</X>
      <Y>26</Y>
      <Z>0</Z>
    </rotation>
    <scale>
      <X>20.04998</X>
      <Y>8.000012</Y>
      <Z>1</Z>
    </scale>
  </PropXMLStruct2>
</ArrayOfPropXMLStruct2>