<?xml version="1.0" encoding="utf-8"?>
<ArrayOfParticleEmitterXmlMedium xmlns:xsi="http://www.w3.org/2001/XMLSchema-instance" xmlns:xsd="http://www.w3.org/2001/XMLSchema">
  <ParticleEmitterXmlMedium>
    <TexID>0</TexID>
    <Position>
      <X>-51668.4727</X>
      <Y>-953.732056</Y>
      <Z>-24254.6387</Z>
    </Position>
    <MaxParticles>250</MaxParticles>
    <MaxDistance>2000</MaxDistance>
    <MaxLife>10000</MaxLife>
    <Spread>0.11</Spread>
    <SpawnRadius>
      <X>435</X>
      <Y>26</Y>
      <Z>476</Z>
    </SpawnRadius>
    <Frequency>75</Frequency>
    <GrowForMillies>200</GrowForMillies>
    <ShrinkForMillies>500</ShrinkForMillies>
    <ShowForMillies>500</ShowForMillies>
    <FadeForMillies>500</FadeForMillies>
    <Speed>
      <X>-0.4</X>
      <Y>-1.7</Y>
      <Z>0</Z>
    </Speed>
    <SpeedVariance>0.5</SpeedVariance>
  </ParticleEmitterXmlMedium>
  <ParticleEmitterXmlMedium>
    <TexID>0</TexID>
    <Position>
      <X>-26509.623</X>
      <Y>-1967.58337</Y>
      <Z>-21782.8535</Z>
    </Position>
    <MaxParticles>150</MaxParticles>
    <MaxDistance>1000</MaxDistance>
    <MaxLife>5000</MaxLife>
    <Spread>0.01</Spread>
    <SpawnRadius>
      <X>473</X>
      <Y>281</Y>
      <Z>527</Z>
    </SpawnRadius>
    <Frequency>25</Frequency>
    <GrowForMillies>500</GrowForMillies>
    <ShrinkForMillies>500</ShrinkForMillies>
    <ShowForMillies>0</ShowForMillies>
    <FadeForMillies>0</FadeForMillies>
    <Speed>
      <X>0</X>
      <Y>-1.5</Y>
      <Z>0</Z>
    </Speed>
    <SpeedVariance>0.5</SpeedVariance>
  </ParticleEmitterXmlMedium>
  <ParticleEmitterXmlMedium>
    <TexID>0</TexID>
    <Position>
      <X>-23193.8145</X>
      <Y>-1300.70435</Y>
      <Z>-25310.8027</Z>
    </Position>
    <MaxParticles>150</MaxParticles>
    <MaxDistance>1000</MaxDistance>
    <MaxLife>5000</MaxLife>
    <Spread>0.01</Spread>
    <SpawnRadius>
      <X>1632</X>
      <Y>378</Y>
      <Z>1802</Z>
    </SpawnRadius>
    <Frequency>25</Frequency>
    <GrowForMillies>500</GrowForMillies>
    <ShrinkForMillies>500</ShrinkForMillies>
    <ShowForMillies>0</ShowForMillies>
    <FadeForMillies>0</FadeForMillies>
    <Speed>
      <X>0</X>
      <Y>-1.5</Y>
      <Z>0</Z>
    </Speed>
    <SpeedVariance>0.5</SpeedVariance>
  </ParticleEmitterXmlMedium>
  <ParticleEmitterXmlMedium>
    <TexID>0</TexID>
    <Position>
      <X>-26874.2148</X>
      <Y>-2144.163</Y>
      <Z>-19266.0586</Z>
    </Position>
    <MaxParticles>300</MaxParticles>
    <MaxDistance>1000</MaxDistance>
    <MaxLife>5000</MaxLife>
    <Spread>0.01</Spread>
    <SpawnRadius>
      <X>531</X>
      <Y>320</Y>
      <Z>537</Z>
    </SpawnRadius>
    <Frequency>25</Frequency>
    <GrowForMillies>300</GrowForMillies>
    <ShrinkForMillies>500</ShrinkForMillies>
    <ShowForMillies>0</ShowForMillies>
    <FadeForMillies>0</FadeForMillies>
    <Speed>
      <X>0</X>
      <Y>-1.5</Y>
      <Z>0</Z>
    </Speed>
    <SpeedVariance>0.5</SpeedVariance>
  </ParticleEmitterXmlMedium>
  <ParticleEmitterXmlMedium>
    <TexID>0</TexID>
    <Position>
      <X>-6285.237</X>
      <Y>-3264.95972</Y>
      <Z>-40742.8164</Z>
    </Position>
    <MaxParticles>200</MaxParticles>
    <MaxDistance>1000</MaxDistance>
    <MaxLife>5000</MaxLife>
    <Spread>0.01</Spread>
    <SpawnRadius>
      <X>1554</X>
      <Y>277</Y>
      <Z>1802</Z>
    </SpawnRadius>
    <Frequency>25</Frequency>
    <GrowForMillies>500</GrowForMillies>
    <ShrinkForMillies>500</ShrinkForMillies>
    <ShowForMillies>0</ShowForMillies>
    <FadeForMillies>0</FadeForMillies>
    <Speed>
      <X>0</X>
      <Y>-1.5</Y>
      <Z>0</Z>
    </Speed>
    <SpeedVariance>0.5</SpeedVariance>
  </ParticleEmitterXmlMedium>
  <ParticleEmitterXmlMedium>
    <TexID>0</TexID>
    <Position>
      <X>-23881.9023</X>
      <Y>-2665.39453</Y>
      <Z>-50228.02</Z>
    </Position>
    <MaxParticles>200</MaxParticles>
    <MaxDistance>1000</MaxDistance>
    <MaxLife>5000</MaxLife>
    <Spread>0.01</Spread>
    <SpawnRadius>
      <X>1046</X>
      <Y>262</Y>
      <Z>1043</Z>
    </SpawnRadius>
    <Frequency>25</Frequency>
    <GrowForMillies>500</GrowForMillies>
    <ShrinkForMillies>500</ShrinkForMillies>
    <ShowForMillies>0</ShowForMillies>
    <FadeForMillies>0</FadeForMillies>
    <Speed>
      <X>0</X>
      <Y>-1.5</Y>
      <Z>0</Z>
    </Speed>
    <SpeedVariance>0.5</SpeedVariance>
  </ParticleEmitterXmlMedium>
  <ParticleEmitterXmlMedium>
    <TexID>1</TexID>
    <Position>
      <X>-26409.666</X>
      <Y>-3425.7644</Y>
      <Z>-55169.9727</Z>
    </Position>
    <MaxParticles>300</MaxParticles>
    <MaxDistance>1000</MaxDistance>
    <MaxLife>1200</MaxLife>
    <Spread>0.03</Spread>
    <SpawnRadius>
      <X>385</X>
      <Y>83</Y>
      <Z>268</Z>
    </SpawnRadius>
    <Frequency>5</Frequency>
    <GrowForMillies>200</GrowForMillies>
    <ShrinkForMillies>1000</ShrinkForMillies>
    <ShowForMillies>0</ShowForMillies>
    <FadeForMillies>0</FadeForMillies>
    <Speed>
      <X>0.1</X>
      <Y>1.5</Y>
      <Z>-0.1</Z>
    </Speed>
    <SpeedVariance>0.2</SpeedVariance>
  </ParticleEmitterXmlMedium>
</ArrayOfParticleEmitterXmlMedium>